django_stackoverflow_trace
