Metadata-Version: 1.1
Name: django-stackoverflow-trace
Version: 0.0.4
Summary: A custom Django technical error template that puts a stackoverflow search link above the related exception message.
Home-page: https://github.com/emre/django-stackoverflow-trace
Author: Emre Yilmaz
Author-email: mail@emreyilmaz.me
License: MIT
Platform: UNKNOWN
Classifier: Programming Language :: Python
Classifier: Programming Language :: Python :: 2.7
